vps/__init__.py
vps/argparse_helper.py
vps/crontab.py
vps/decode
vps/linuxtools.py
vps/network.py
vps/utils.py
vps/toolkits/__init__.py
vps/toolkits/telegram.py
vpstool-0.0.7.dist-info/LICENSE
vpstool-0.0.7.dist-info/METADATA
vpstool-0.0.7.dist-info/WHEEL
vpstool-0.0.7.dist-info/entry_points.txt
vpstool-0.0.7.dist-info/top_level.txt
vpstool-0.0.7.dist-info/RECORD
