Metadata-Version: 2.1
Name: vpstool
Version: 0.0.7
Summary: VPS toolkits
Home-page: https://github.com/GaoangLiu/vpstool
Author: SLP
Author-email: byteleap@gmail.com
License: UNKNOWN
Platform: UNKNOWN
Classifier: Programming Language :: Python :: 3
Classifier: License :: OSI Approved :: MIT License
Classifier: Operating System :: OS Independent
Requires-Dist: colorlog (>=4.6.1)
Requires-Dist: tqdm
Requires-Dist: lxml
Requires-Dist: requests
Requires-Dist: dofast
Requires-Dist: smart-open
Requires-Dist: pillow
Requires-Dist: bs4
Requires-Dist: arrow
Requires-Dist: numpy
Requires-Dist: termcolor
Requires-Dist: pycrypto
